modeyolo/__init__.py
modeyolo/ColorOperation.py
modeyolo/DatasetModifier.py
modeyolo/ModelTrain.py
modeyolo-0.2.5.dist-info/LICENSE
modeyolo-0.2.5.dist-info/METADATA
modeyolo-0.2.5.dist-info/WHEEL
modeyolo-0.2.5.dist-info/RECORD
