Metadata-Version: 2.1
Name: modeyolo
Version: 0.2.5
Summary: ModeYOLO is a versatile Python package designed for efficient color space transformations and simplified dataset modification for deep learning applications. Seamlessly integrating into your workflow, this package empowers users to effortlessly perform diverse color operations and streamline the creation of modified datasets, enhancing the flexibility and convenience of machine learning model training processes.
Home-page: https://github.com/colddsam/ModeYOLO.git
License: MIT
Keywords: Color Space Transformations,Image Processing,Deep Learning,Dataset Modification,Computer Vision,OpenCV,NumPy,Data Augmentation,Machine Learning,Python Package
Author: colddsam
Author-email: dassamratkumar772@gmail.com
Requires-Python: >=3.10,<4.0
Classifier: License :: OSI Approved :: MIT License
Classifier: Programming Language :: Python :: 3
Classifier: Programming Language :: Python :: 3.10
Classifier: Programming Language :: Python :: 3.11
Classifier: Programming Language :: Python :: 3.12
Requires-Dist: opencv-python (>=4.9.0.80,<5.0.0.0)
Requires-Dist: pyyaml (>=6.0.1,<7.0.0)
Requires-Dist: tqdm (>=4.66.2,<5.0.0)
Requires-Dist: ultralytics (>=8.1.25,<9.0.0)
Project-URL: Repository, https://github.com/colddsam/ModeYOLO.git
